{"nodes": [{"id": "c_users_aryaman_documents_ai_tool_bii_agent_harness_src_renderer_components_chat_messagebubble_tsx", "label": "MessageBubble.tsx", "file_type": "code", "source_file": "C:\\Users\\Aryaman\\Documents\\AI Tool\\BII Agent Harness\\src\\renderer\\components\\Chat\\MessageBubble.tsx", "source_location": "L1"}, {"id": "messagebubble_safeurl", "label": "safeUrl()", "file_type": "code", "source_file": "C:\\Users\\Aryaman\\Documents\\AI Tool\\BII Agent Harness\\src\\renderer\\components\\Chat\\MessageBubble.tsx", "source_location": "L7"}, {"id": "messagebubble_cacheattachments", "label": "cacheAttachments()", "file_type": "code", "source_file": "C:\\Users\\Aryaman\\Documents\\AI Tool\\BII Agent Harness\\src\\renderer\\components\\Chat\\MessageBubble.tsx", "source_location": "L26"}, {"id": "messagebubble_clearattachmentcache", "label": "clearAttachmentCache()", "file_type": "code", "source_file": "C:\\Users\\Aryaman\\Documents\\AI Tool\\BII Agent Harness\\src\\renderer\\components\\Chat\\MessageBubble.tsx", "source_location": "L34"}], "edges": [{"source": "c_users_aryaman_documents_ai_tool_bii_agent_harness_src_renderer_components_chat_messagebubble_tsx", "target": "react_markdown", "relation": "imports_from", "confidence": "EXTRACTED", "source_file": "C:\\Users\\Aryaman\\Documents\\AI Tool\\BII Agent Harness\\src\\renderer\\components\\Chat\\MessageBubble.tsx", "source_location": "L1", "weight": 1.0}, {"source": "c_users_aryaman_documents_ai_tool_bii_agent_harness_src_renderer_components_chat_messagebubble_tsx", "target": "react", "relation": "imports_from", "confidence": "EXTRACTED", "source_file": "C:\\Users\\Aryaman\\Documents\\AI Tool\\BII Agent Harness\\src\\renderer\\components\\Chat\\MessageBubble.tsx", "source_location": "L2", "weight": 1.0}, {"source": "c_users_aryaman_documents_ai_tool_bii_agent_harness_src_renderer_components_chat_messagebubble_tsx", "target": "c_users_aryaman_documents_ai_tool_bii_agent_harness_src_renderer_components_chat_attachmentrow", "relation": "imports_from", "confidence": "EXTRACTED", "source_file": "C:\\Users\\Aryaman\\Documents\\AI Tool\\BII Agent Harness\\src\\renderer\\components\\Chat\\MessageBubble.tsx", "source_location": "L3", "weight": 1.0}, {"source": "c_users_aryaman_documents_ai_tool_bii_agent_harness_src_renderer_components_chat_messagebubble_tsx", "target": "c_users_aryaman_documents_ai_tool_bii_agent_harness_src_renderer_ipc", "relation": "imports_from", "confidence": "EXTRACTED", "source_file": "C:\\Users\\Aryaman\\Documents\\AI Tool\\BII Agent Harness\\src\\renderer\\components\\Chat\\MessageBubble.tsx", "source_location": "L4", "weight": 1.0}, {"source": "c_users_aryaman_documents_ai_tool_bii_agent_harness_src_renderer_components_chat_messagebubble_tsx", "target": "c_users_aryaman_documents_ai_tool_bii_agent_harness_src_shared_types", "relation": "imports_from", "confidence": "EXTRACTED", "source_file": "C:\\Users\\Aryaman\\Documents\\AI Tool\\BII Agent Harness\\src\\renderer\\components\\Chat\\MessageBubble.tsx", "source_location": "L5", "weight": 1.0}, {"source": "c_users_aryaman_documents_ai_tool_bii_agent_harness_src_renderer_components_chat_messagebubble_tsx", "target": "messagebubble_safeurl", "relation": "contains", "confidence": "EXTRACTED", "source_file": "C:\\Users\\Aryaman\\Documents\\AI Tool\\BII Agent Harness\\src\\renderer\\components\\Chat\\MessageBubble.tsx", "source_location": "L7", "weight": 1.0}, {"source": "c_users_aryaman_documents_ai_tool_bii_agent_harness_src_renderer_components_chat_messagebubble_tsx", "target": "messagebubble_cacheattachments", "relation": "contains", "confidence": "EXTRACTED", "source_file": "C:\\Users\\Aryaman\\Documents\\AI Tool\\BII Agent Harness\\src\\renderer\\components\\Chat\\MessageBubble.tsx", "source_location": "L26", "weight": 1.0}, {"source": "c_users_aryaman_documents_ai_tool_bii_agent_harness_src_renderer_components_chat_messagebubble_tsx", "target": "messagebubble_clearattachmentcache", "relation": "contains", "confidence": "EXTRACTED", "source_file": "C:\\Users\\Aryaman\\Documents\\AI Tool\\BII Agent Harness\\src\\renderer\\components\\Chat\\MessageBubble.tsx", "source_location": "L34", "weight": 1.0}], "raw_calls": [{"caller_nid": "messagebubble_safeurl", "callee": "startsWith", "source_file": "C:\\Users\\Aryaman\\Documents\\AI Tool\\BII Agent Harness\\src\\renderer\\components\\Chat\\MessageBubble.tsx", "source_location": "L18"}, {"caller_nid": "messagebubble_safeurl", "callee": "startsWith", "source_file": "C:\\Users\\Aryaman\\Documents\\AI Tool\\BII Agent Harness\\src\\renderer\\components\\Chat\\MessageBubble.tsx", "source_location": "L18"}, {"caller_nid": "messagebubble_cacheattachments", "callee": "next", "source_file": "C:\\Users\\Aryaman\\Documents\\AI Tool\\BII Agent Harness\\src\\renderer\\components\\Chat\\MessageBubble.tsx", "source_location": "L28"}, {"caller_nid": "messagebubble_cacheattachments", "callee": "keys", "source_file": "C:\\Users\\Aryaman\\Documents\\AI Tool\\BII Agent Harness\\src\\renderer\\components\\Chat\\MessageBubble.tsx", "source_location": "L28"}, {"caller_nid": "messagebubble_cacheattachments", "callee": "delete", "source_file": "C:\\Users\\Aryaman\\Documents\\AI Tool\\BII Agent Harness\\src\\renderer\\components\\Chat\\MessageBubble.tsx", "source_location": "L29"}, {"caller_nid": "messagebubble_cacheattachments", "callee": "set", "source_file": "C:\\Users\\Aryaman\\Documents\\AI Tool\\BII Agent Harness\\src\\renderer\\components\\Chat\\MessageBubble.tsx", "source_location": "L31"}, {"caller_nid": "messagebubble_clearattachmentcache", "callee": "clear", "source_file": "C:\\Users\\Aryaman\\Documents\\AI Tool\\BII Agent Harness\\src\\renderer\\components\\Chat\\MessageBubble.tsx", "source_location": "L35"}]}