{"nodes": [{"id": "c_users_aryaman_documents_ai_tool_bii_agent_harness_src_renderer_components_wizard_setupwizard_tsx", "label": "SetupWizard.tsx", "file_type": "code", "source_file": "C:\\Users\\Aryaman\\Documents\\AI Tool\\BII Agent Harness\\src\\renderer\\components\\Wizard\\SetupWizard.tsx", "source_location": "L1"}, {"id": "setupwizard_handlestep1", "label": "handleStep1()", "file_type": "code", "source_file": "C:\\Users\\Aryaman\\Documents\\AI Tool\\BII Agent Harness\\src\\renderer\\components\\Wizard\\SetupWizard.tsx", "source_location": "L22"}, {"id": "setupwizard_handlestep2", "label": "handleStep2()", "file_type": "code", "source_file": "C:\\Users\\Aryaman\\Documents\\AI Tool\\BII Agent Harness\\src\\renderer\\components\\Wizard\\SetupWizard.tsx", "source_location": "L26"}, {"id": "setupwizard_handleback", "label": "handleBack()", "file_type": "code", "source_file": "C:\\Users\\Aryaman\\Documents\\AI Tool\\BII Agent Harness\\src\\renderer\\components\\Wizard\\SetupWizard.tsx", "source_location": "L27"}, {"id": "setupwizard_handlecomplete", "label": "handleComplete()", "file_type": "code", "source_file": "C:\\Users\\Aryaman\\Documents\\AI Tool\\BII Agent Harness\\src\\renderer\\components\\Wizard\\SetupWizard.tsx", "source_location": "L31"}], "edges": [{"source": "c_users_aryaman_documents_ai_tool_bii_agent_harness_src_renderer_components_wizard_setupwizard_tsx", "target": "react", "relation": "imports_from", "confidence": "EXTRACTED", "source_file": "C:\\Users\\Aryaman\\Documents\\AI Tool\\BII Agent Harness\\src\\renderer\\components\\Wizard\\SetupWizard.tsx", "source_location": "L1", "weight": 1.0}, {"source": "c_users_aryaman_documents_ai_tool_bii_agent_harness_src_renderer_components_wizard_setupwizard_tsx", "target": "c_users_aryaman_documents_ai_tool_bii_agent_harness_src_renderer_components_wizard_wizardstep1", "relation": "imports_from", "confidence": "EXTRACTED", "source_file": "C:\\Users\\Aryaman\\Documents\\AI Tool\\BII Agent Harness\\src\\renderer\\components\\Wizard\\SetupWizard.tsx", "source_location": "L2", "weight": 1.0}, {"source": "c_users_aryaman_documents_ai_tool_bii_agent_harness_src_renderer_components_wizard_setupwizard_tsx", "target": "c_users_aryaman_documents_ai_tool_bii_agent_harness_src_renderer_components_wizard_wizardstep2", "relation": "imports_from", "confidence": "EXTRACTED", "source_file": "C:\\Users\\Aryaman\\Documents\\AI Tool\\BII Agent Harness\\src\\renderer\\components\\Wizard\\SetupWizard.tsx", "source_location": "L3", "weight": 1.0}, {"source": "c_users_aryaman_documents_ai_tool_bii_agent_harness_src_renderer_components_wizard_setupwizard_tsx", "target": "c_users_aryaman_documents_ai_tool_bii_agent_harness_src_renderer_components_wizard_wizardstep3", "relation": "imports_from", "confidence": "EXTRACTED", "source_file": "C:\\Users\\Aryaman\\Documents\\AI Tool\\BII Agent Harness\\src\\renderer\\components\\Wizard\\SetupWizard.tsx", "source_location": "L4", "weight": 1.0}, {"source": "c_users_aryaman_documents_ai_tool_bii_agent_harness_src_renderer_components_wizard_setupwizard_tsx", "target": "c_users_aryaman_documents_ai_tool_bii_agent_harness_src_renderer_ipc", "relation": "imports_from", "confidence": "EXTRACTED", "source_file": "C:\\Users\\Aryaman\\Documents\\AI Tool\\BII Agent Harness\\src\\renderer\\components\\Wizard\\SetupWizard.tsx", "source_location": "L5", "weight": 1.0}, {"source": "c_users_aryaman_documents_ai_tool_bii_agent_harness_src_renderer_components_wizard_setupwizard_tsx", "target": "setupwizard_handlestep1", "relation": "contains", "confidence": "EXTRACTED", "source_file": "C:\\Users\\Aryaman\\Documents\\AI Tool\\BII Agent Harness\\src\\renderer\\components\\Wizard\\SetupWizard.tsx", "source_location": "L22", "weight": 1.0}, {"source": "c_users_aryaman_documents_ai_tool_bii_agent_harness_src_renderer_components_wizard_setupwizard_tsx", "target": "setupwizard_handlestep2", "relation": "contains", "confidence": "EXTRACTED", "source_file": "C:\\Users\\Aryaman\\Documents\\AI Tool\\BII Agent Harness\\src\\renderer\\components\\Wizard\\SetupWizard.tsx", "source_location": "L26", "weight": 1.0}, {"source": "c_users_aryaman_documents_ai_tool_bii_agent_harness_src_renderer_components_wizard_setupwizard_tsx", "target": "setupwizard_handleback", "relation": "contains", "confidence": "EXTRACTED", "source_file": "C:\\Users\\Aryaman\\Documents\\AI Tool\\BII Agent Harness\\src\\renderer\\components\\Wizard\\SetupWizard.tsx", "source_location": "L27", "weight": 1.0}, {"source": "c_users_aryaman_documents_ai_tool_bii_agent_harness_src_renderer_components_wizard_setupwizard_tsx", "target": "setupwizard_handlecomplete", "relation": "contains", "confidence": "EXTRACTED", "source_file": "C:\\Users\\Aryaman\\Documents\\AI Tool\\BII Agent Harness\\src\\renderer\\components\\Wizard\\SetupWizard.tsx", "source_location": "L31", "weight": 1.0}], "raw_calls": [{"caller_nid": "setupwizard_handlestep1", "callee": "setStatuses", "source_file": "C:\\Users\\Aryaman\\Documents\\AI Tool\\BII Agent Harness\\src\\renderer\\components\\Wizard\\SetupWizard.tsx", "source_location": "L23"}, {"caller_nid": "setupwizard_handlestep1", "callee": "setStep", "source_file": "C:\\Users\\Aryaman\\Documents\\AI Tool\\BII Agent Harness\\src\\renderer\\components\\Wizard\\SetupWizard.tsx", "source_location": "L24"}, {"caller_nid": "setupwizard_handlestep2", "callee": "setStep", "source_file": "C:\\Users\\Aryaman\\Documents\\AI Tool\\BII Agent Harness\\src\\renderer\\components\\Wizard\\SetupWizard.tsx", "source_location": "L26"}, {"caller_nid": "setupwizard_handleback", "callee": "setStatuses", "source_file": "C:\\Users\\Aryaman\\Documents\\AI Tool\\BII Agent Harness\\src\\renderer\\components\\Wizard\\SetupWizard.tsx", "source_location": "L28"}, {"caller_nid": "setupwizard_handleback", "callee": "setStep", "source_file": "C:\\Users\\Aryaman\\Documents\\AI Tool\\BII Agent Harness\\src\\renderer\\components\\Wizard\\SetupWizard.tsx", "source_location": "L29"}, {"caller_nid": "setupwizard_handlecomplete", "callee": "markWizardDone", "source_file": "C:\\Users\\Aryaman\\Documents\\AI Tool\\BII Agent Harness\\src\\renderer\\components\\Wizard\\SetupWizard.tsx", "source_location": "L32"}, {"caller_nid": "setupwizard_handlecomplete", "callee": "setItem", "source_file": "C:\\Users\\Aryaman\\Documents\\AI Tool\\BII Agent Harness\\src\\renderer\\components\\Wizard\\SetupWizard.tsx", "source_location": "L33"}, {"caller_nid": "setupwizard_handlecomplete", "callee": "onComplete", "source_file": "C:\\Users\\Aryaman\\Documents\\AI Tool\\BII Agent Harness\\src\\renderer\\components\\Wizard\\SetupWizard.tsx", "source_location": "L34"}]}